{
    "status": "success",
    "code": 1,
    "message": "questions found",
    "document": {
        "pageno": 1,
        "pagesize": 10,
        "total_count": "10",
        "records": [{
                "prodID": "02",
                "image": "Double Garage Doro.webp",
                "title": "Double Garage Door",
                "amount": 6000.00,
                "catID": "001",
                "qty": 0,
                "item_total_amt": 0
            },
            {
                "prodID": "03",
                "image": "shopping (1).webp",
                "title": "Roof tile ",
                "amount": 10.00,
                "catID": "001",
                "qty": 0,
                "item_total_amt": 0
            },
            {
                "prodID": "07",
                "image": "fence.webp",
                "title": "Fence Diamond Mesh (1200x75 x 30m x 1.8mm)",
                "amount": 1199.00,
                "catID": "002",
                "qty": 0,
                "item_total_amt": 0
            },

            {
                "prodID": "10",
                "image": "Reinforce.webp",
                "title": "Steel Reinforce (Y-Bar) 6m",
                "amount": 78.00,
                "catID": "002",
                "qty": 0,
                "item_total_amt": 0
            },
            {
                "prodID": "15",
                "image": "Block 140MM.webp",
                "title": "Building Block !40MM",
                "amount": 12.00,
                "catID": "001",
                "qty": 0,
                "item_total_amt": 0
            },
            {
                "prodID": "17",
                "image": "Timber.webp",
                "title": "Pine Timber Battens",
                "amount": 38.00,
                "catID": "002",
                "qty": 0,
                "item_total_amt": 0
            },
            {
                "prodID": "18",
                "image": "MelaWood.webp",
                "title": "MelaWood Counter Top",
                "amount": 900.00,
                "catID": "006",
                "qty": 0,
                "item_total_amt": 0
            },
            {
                "prodID": "19",
                "image": "Postfom.webp",
                "title": "Postform Marron Gloss Counter Top",
                "amount": 1000.00,
                "catID": "006",
                "qty": 0,
                "item_total_amt": 0
            },
            {
                "prodID": "21",
                "image": "stones.webp",
                "title": "Crushed Stones 8 Ton",
                "amount": 5800.00,
                "catID": "001",
                "qty": 0,
                "item_total_amt": 0
            },
            {
                "prodID": "23",
                "image": "Sand.webp",
                "title": "Building Sand 6 Cubes",
                "amount": 1800.00,
                "catID": "001",
                "qty": 0,
                "item_total_amt": 0
            },
            {
                "prodID": "24",
                "image": "Brick.webp",
                "title": "Cement brick Stock 7mpa",
                "amount": 2.00,
                "catID": "001",
                "qty": 0,
                "item_total_amt": 0
            },
            {
                "prodID": "25",
                "image": "cement.webp",
                "title": "Afrisam 42.5n All Purpose Cement",
                "amount": 98.00,
                "catID": "001",
                "qty": 0,
                "item_total_amt": 0
            }

        ]
    }
}
